pyserver_http/__main__.py
pyserver_http/server.py
pyserver_http/utils.py
pyserver_http-1.1.0.dist-info/LICENSE
pyserver_http-1.1.0.dist-info/METADATA
pyserver_http-1.1.0.dist-info/WHEEL
pyserver_http-1.1.0.dist-info/entry_points.txt
pyserver_http-1.1.0.dist-info/top_level.txt
pyserver_http-1.1.0.dist-info/RECORD
