Metadata-Version: 2.1
Name: pyserver_http
Version: 1.1.0
Summary: simple http server in python
Author-email: sctech <gamerselimiko@gmail.com>
Project-URL: homepage, https://github.com/sctech-tr/pyserver
Classifier: Programming Language :: Python :: 3
Classifier: Programming Language :: Python :: 3.12
Classifier: Programming Language :: Python :: 3.13
Classifier: Programming Language :: Python :: 3.9
Classifier: License :: OSI Approved :: GNU Affero General Public License v3 or later (AGPLv3+)
Classifier: Operating System :: OS Independent
Requires-Python: >=3.9
License-File: LICENSE
